pip_search/__init__.py
pip_search/__main__.py
pip_search/pip_search.py
pip_search_color-0.2.7.dist-info/LICENSE
pip_search_color-0.2.7.dist-info/METADATA
pip_search_color-0.2.7.dist-info/WHEEL
pip_search_color-0.2.7.dist-info/entry_points.txt
pip_search_color-0.2.7.dist-info/top_level.txt
pip_search_color-0.2.7.dist-info/RECORD
